pytorch_bsf-0.13.2.dist-info/licenses/LICENSE
tests/__init__.py
tests/bezier_simplex.py
tests/control_points.py
tests/validator.py
torch_bsf/__init__.py
torch_bsf/__main__.py
torch_bsf/bezier_simplex.py
torch_bsf/control_points.py
torch_bsf/preprocessing.py
torch_bsf/py.typed
torch_bsf/validator.py
torch_bsf/model_selection/__init__.py
torch_bsf/model_selection/elastic_net_grid.py
torch_bsf/model_selection/kfold.py
pytorch_bsf-0.13.2.dist-info/METADATA
pytorch_bsf-0.13.2.dist-info/WHEEL
pytorch_bsf-0.13.2.dist-info/top_level.txt
pytorch_bsf-0.13.2.dist-info/RECORD
