Metadata-Version: 2.4
Name: pytorch-bsf
Version: 0.13.2
Summary: PyTorch implementation of Bezier simplex fitting
Home-page: https://github.com/rafcc/pytorch-bsf
Author: RIKEN AIP-FUJITSU Collaboration Center (RAFCC)
Author-email: hmkz@s101.xrea.com
License: MIT
Classifier: Development Status :: 3 - Alpha
Classifier: Environment :: Console
Classifier: Intended Audience :: Developers
Classifier: Intended Audience :: Education
Classifier: Intended Audience :: Science/Research
Classifier: License :: OSI Approved :: MIT License
Classifier: Operating System :: POSIX
Classifier: Programming Language :: Python
Classifier: Programming Language :: Python :: 3.10
Classifier: Programming Language :: Python :: 3.11
Classifier: Programming Language :: Python :: 3.12
Classifier: Programming Language :: Python :: 3.13
Classifier: Topic :: Scientific/Engineering
Classifier: Topic :: Scientific/Engineering :: Artificial Intelligence
Classifier: Topic :: Scientific/Engineering :: Mathematics
Classifier: Topic :: Software Development
Classifier: Topic :: Software Development :: Libraries
Classifier: Topic :: Software Development :: Libraries :: Python Modules
Requires-Python: >=3.10
License-File: LICENSE
Requires-Dist: setuptools>=21.0.0
Requires-Dist: torch
Requires-Dist: lightning
Requires-Dist: pl-crossvalidate
Requires-Dist: protobuf
Requires-Dist: mlflow
Requires-Dist: jsonschema
Requires-Dist: PyYAML
Provides-Extra: develop
Requires-Dist: isort; extra == "develop"
Requires-Dist: black; extra == "develop"
Requires-Dist: tox; extra == "develop"
Requires-Dist: pytest; extra == "develop"
Requires-Dist: pytest-cov; extra == "develop"
Requires-Dist: pytest-randomly; extra == "develop"
Requires-Dist: mypy; extra == "develop"
Requires-Dist: types-jsonschema; extra == "develop"
Requires-Dist: types-PyYAML; extra == "develop"
Requires-Dist: types-setuptools; extra == "develop"
Dynamic: license-file
